clearskies/__init__.py
clearskies/action.py
clearskies/column.py
clearskies/configurable.py
clearskies/decorators.py
clearskies/decorators.pyi
clearskies/end.py
clearskies/endpoint.py
clearskies/endpoint_group.py
clearskies/environment.py
clearskies/loggable.py
clearskies/model.py
clearskies/py.typed
clearskies/schema.py
clearskies/security_header.py
clearskies/typing.py
clearskies/validator.py
clearskies/authentication/__init__.py
clearskies/authentication/authentication.py
clearskies/authentication/authorization.py
clearskies/authentication/authorization_pass_through.py
clearskies/authentication/jwks.py
clearskies/authentication/public.py
clearskies/authentication/secret_bearer.py
clearskies/autodoc/__init__.py
clearskies/autodoc/py.typed
clearskies/autodoc/formats/__init__.py
clearskies/autodoc/formats/oai3_json/__init__.py
clearskies/autodoc/formats/oai3_json/oai3_json.py
clearskies/autodoc/formats/oai3_json/oai3_schema_resolver.py
clearskies/autodoc/formats/oai3_json/parameter.py
clearskies/autodoc/formats/oai3_json/request.py
clearskies/autodoc/formats/oai3_json/response.py
clearskies/autodoc/formats/oai3_json/test.json
clearskies/autodoc/formats/oai3_json/schema/__init__.py
clearskies/autodoc/formats/oai3_json/schema/array.py
clearskies/autodoc/formats/oai3_json/schema/default.py
clearskies/autodoc/formats/oai3_json/schema/enum.py
clearskies/autodoc/formats/oai3_json/schema/object.py
clearskies/autodoc/request/__init__.py
clearskies/autodoc/request/header.py
clearskies/autodoc/request/json_body.py
clearskies/autodoc/request/parameter.py
clearskies/autodoc/request/request.py
clearskies/autodoc/request/url_parameter.py
clearskies/autodoc/request/url_path.py
clearskies/autodoc/response/__init__.py
clearskies/autodoc/response/response.py
clearskies/autodoc/schema/__init__.py
clearskies/autodoc/schema/array.py
clearskies/autodoc/schema/base64.py
clearskies/autodoc/schema/boolean.py
clearskies/autodoc/schema/date.py
clearskies/autodoc/schema/datetime.py
clear_skies-2.0.27.dist-info/METADATA
clear_skies-2.0.27.dist-info/WHEEL
clear_skies-2.0.27.dist-info/licenses/LICENSE
clear_skies-2.0.27.dist-info/RECORD
