Metadata-Version: 2.4
Name: clear-skies
Version: 2.0.27
Summary: A framework for building backends in the cloud
Project-URL: Documentation, https://clearskies.io/
Project-URL: Repository, https://github.com/clearskies-py/clearskies
Project-URL: Issues, https://github.com/clearskies-py/clearskies/issues
Project-URL: Changelog, https://github.com/clearskies-py/clearskies/blob/main/CHANGELOG.md
Author-email: Conor Mancone <cmancone@gmail.com>
License-Expression: MIT
License-File: LICENSE
Classifier: Development Status :: 5 - Production/Stable
Classifier: Intended Audience :: Developers
Classifier: License :: OSI Approved :: MIT License
Classifier: Programming Language :: Python :: 3
Requires-Python: <4.0,>=3.11
Requires-Dist: dateparser<2.0.0,>=1.1.8
Requires-Dist: requests<3.0.0,>=2.31.0
Requires-Dist: typing-extensions<5.0.0,>=4.12.0; python_version >= '3.10' and python_version < '3.11'
Requires-Dist: wrapt<2.0.0,>=1.16.0
Provides-Extra: graphql
Requires-Dist: gql[all]>=4.0.0; extra == 'graphql'
Provides-Extra: jwcrypto
Requires-Dist: jwcrypto<2.0.0,>=1.5.6; extra == 'jwcrypto'
Provides-Extra: mysql
Requires-Dist: pymysql<2.0.0,>=1.1.0; extra == 'mysql'
Provides-Extra: pgsql
Requires-Dist: psycopg[binary]<4.0.0,>=3.1.10; extra == 'pgsql'
Provides-Extra: secrets
Requires-Dist: akeyless-cloud-id<0.3.0,>=0.2.3; extra == 'secrets'
Requires-Dist: akeyless<5.0.0,>=4.0.0; extra == 'secrets'
